plotjs/__init__.py
plotjs/css.py
plotjs/javascript.py
plotjs/main.py
plotjs/utils.py
plotjs/data/__init__.py
plotjs/data/datasets.py
plotjs/data/iris.csv
plotjs/data/mtcars.csv
plotjs/data/titanic.csv
plotjs/static/default.css
plotjs/static/plotparser.js
plotjs/static/template.html
plotjs-0.0.5.dist-info/licenses/LICENSE
plotjs-0.0.5.dist-info/METADATA
plotjs-0.0.5.dist-info/WHEEL
plotjs-0.0.5.dist-info/top_level.txt
plotjs-0.0.5.dist-info/RECORD
